langchain_baichuan/__init__.py
langchain_baichuan-0.0.1.dist-info/LICENSE
langchain_baichuan-0.0.1.dist-info/METADATA
langchain_baichuan-0.0.1.dist-info/WHEEL
langchain_baichuan-0.0.1.dist-info/RECORD
